prudence/__init__.py
prudence/__version__.py
prudence-0.0.2.dist-info/LICENSE
prudence-0.0.2.dist-info/METADATA
prudence-0.0.2.dist-info/WHEEL
prudence-0.0.2.dist-info/entry_points.txt
prudence-0.0.2.dist-info/top_level.txt
prudence-0.0.2.dist-info/RECORD
